temper_pygments/__init__.py
temper_pygments/adapt.py
temper_pygments/lexer.py
temper_pygments-0.6.0.dist-info/METADATA
temper_pygments-0.6.0.dist-info/WHEEL
temper_pygments-0.6.0.dist-info/entry_points.txt
temper_pygments-0.6.0.dist-info/RECORD
