Metadata-Version: 2.4
Name: temper-pygments
Version: 0.6.0
Summary: 
Author: Tom
Author-email: tom@temper.systems
Requires-Python: >=3.11,<4.0
Classifier: Programming Language :: Python :: 3
Classifier: Programming Language :: Python :: 3.11
Classifier: Programming Language :: Python :: 3.12
Classifier: Programming Language :: Python :: 3.13
Classifier: Programming Language :: Python :: 3.14
Requires-Dist: pygments (>=2.12.0,<3.0.0)
Requires-Dist: temper-core (==0.6.0)
Requires-Dist: temper-syntax (==0.6.0)
